flight_arbitrage/__init__.py
flight_arbitrage/flight.py
flight_arbitrage/hidden_city.py
flight_arbitrage-1.0.0.dist-info/LICENSE
flight_arbitrage-1.0.0.dist-info/WHEEL
flight_arbitrage-1.0.0.dist-info/METADATA
flight_arbitrage-1.0.0.dist-info/RECORD
