Metadata-Version: 2.1
Name: flight_arbitrage
Version: 1.0.0
Summary: Finds arbitrage in plane ticket prices
Home-page: https://github.com/jrinder42/Flight_Arbitrage
Author: Jordan Rinder
Author-email: jordan.rinder@gmail.com
Requires-Python: >=3.7
Classifier: License :: OSI Approved :: MIT License
Classifier: Programming Language :: Python :: 3.7
Classifier: Programming Language :: Python :: 3.8
Classifier: Programming Language :: Python :: 3.9
